cbsa/ReactionSystem.py
cbsa/SimulationCBSA.py
cbsa/__init__.py
cbsa/cbsa.py
cbsa-0.1.0.dist-info/LICENSE
cbsa-0.1.0.dist-info/METADATA
cbsa-0.1.0.dist-info/WHEEL
cbsa-0.1.0.dist-info/top_level.txt
cbsa-0.1.0.dist-info/RECORD
