Metadata-Version: 2.1
Name: cbsa
Version: 0.1.0
Summary: A Python package to simulate biochemical systems using the Constraint-Based Simulation Algorithm
Home-page: https://github.com/pauloburke/CBSA
Author: Paulo Burke
Author-email: pauloepburke@gmail.com
License: UNKNOWN
Platform: UNKNOWN
Classifier: Programming Language :: Python :: 3
Classifier: License :: OSI Approved :: MIT License
Classifier: Operating System :: OS Independent
Requires-Python: >=3.7
Requires-Dist: numpy
